pydefender/__init__.py
pydefender/__main__.py
pydefender/pydefender/__init__.py
pydefender/pydefender/__main__.py
pydefender-1.0.7.dist-info/METADATA
pydefender-1.0.7.dist-info/WHEEL
pydefender-1.0.7.dist-info/top_level.txt
pydefender-1.0.7.dist-info/RECORD
